{
  "code": 0,
  "data": {
    "records": [
      {
        "examLevelId": "HSK6",
        "children": [],
        "level1Content": "谈论环境问题",
        "level2Content": "能听懂有关自然灾害、能源开发、节能环保、基础设施等环境问题介绍、报道的主要内容。如：洪水、火灾、旱灾等；风能、水能、电能、太阳能等；绿化、低碳生活、减碳减排等；桥梁、建筑物等。"
      },
      {
        "examLevelId": "HSK6",
        "children": [],
        "level1Content": "谈论环境问题",
        "level2Content": "能流畅地向他人介绍自己所了解的有关上述环境问题的主要内容，能与他人交流，发表看法。"
      },
      {
        "examLevelId": "HSK6",
        "children": [],
        "level1Content": "谈论环境问题",
        "level2Content": "能看懂关于上述环境问题的介绍性文章、新闻报道。"
      },
      {
        "examLevelId": "HSK6",
        "children": [],
        "level1Content": "谈论环境问题",
        "level2Content": "能写文章介绍自己了解的上述环境问题的情况，发表看法。"
      }
    ],
    "total": 4,
    "size": 500,
    "current": 1,
    "orders": [],
    "optimizeCountSql": true,
    "searchCount": true,
    "pages": 1
  },
  "ok": true
}
